aws_exporter/__init__.py
aws_exporter/__main__.py
aws_exporter/cli.py
aws_exporter/metrics.py
aws_exporter/util.py
aws_exporter/aws/__init__.py
aws_exporter/aws/backup.py
aws_exporter/aws/ec2.py
aws_exporter/aws/ses.py
aws_exporter/aws/sns.py
aws_exporter/aws/sts.py
tests/__init__.py
tests/util.py
aws_exporter-0.5.1.dist-info/LICENSE.txt
aws_exporter-0.5.1.dist-info/METADATA
aws_exporter-0.5.1.dist-info/WHEEL
aws_exporter-0.5.1.dist-info/entry_points.txt
aws_exporter-0.5.1.dist-info/top_level.txt
aws_exporter-0.5.1.dist-info/RECORD
