Metadata-Version: 2.1
Name: aws-exporter
Version: 0.5.1
Home-page: https://github.com/ClarkSource/aws-exporter
Author: Aljosha Friemann
Author-email: aljosha.friemann@clark.de
Platform: linux
Classifier: Programming Language :: Python :: 3
License-File: LICENSE.txt
Requires-Dist: prometheus-client
Requires-Dist: boto3
